{"10_google.jpeg": [{"Name": "Clothing", "Confidence": 98.72863006591797, "Instances": [], "Parents": [], "Aliases": [{"Name": "Apparel"}], "Categories": [{"Name": "Apparel and Accessories"}]}, {"Name": "Veil", "Confidence": 98.72863006591797, "Instances": [], "Parents": [{"Name": "Clothing"}], "Aliases": [], "Categories": [{"Name": "Apparel and Accessories"}]}, {"Name": "Hoodie", "Confidence": 96.5831527709961, "Instances": [{"BoundingBox": {"Width": 0.7896627187728882, "Height": 0.9995041489601135, "Left": 0.01300552487373352, "Top": 0.0004958721692673862}, "Confidence": 96.5831527709961}], "Parents": [{"Name": "Clothing"}, {"Name": "Knitwear"}, {"Name": "Sweater"}, {"Name": "Sweatshirt"}], "Aliases": [], "Categories": [{"Name": "Apparel and Accessories"}]}, {"Name": "Knitwear", "Confidence": 96.5831527709961, "Instances": [], "Parents": [{"Name": "Clothing"}], "Aliases": [{"Name": "Knitted Clothes"}], "Categories": [{"Name": "Apparel and Accessories"}]}, {"Name": "Sweater", "Confidence": 96.5831527709961, "Instances": [], "Parents": [{"Name": "Clothing"}, {"Name": "Knitwear"}], "Aliases": [], "Categories": [{"Name": "Apparel and Accessories"}]}, {"Name": "Sweatshirt", "Confidence": 96.5831527709961, "Instances": [], "Parents": [{"Name": "Clothing"}, {"Name": "Knitwear"}, {"Name": "Sweater"}], "Aliases": [], "Categories": [{"Name": "Apparel and Accessories"}]}, {"Name": "Fashion", "Confidence": 56.65492248535156, "Instances": [], "Parents": [], "Aliases": [], "Categories": [{"Name": "Apparel and Accessories"}]}], "1_google.jpg": [{"Name": "People", "Confidence": 99.99819946289062, "Instances": [], "Parents": [{"Name": "Person"}], "Aliases": [], "Categories": [{"Name": "Person Description"}]}, {"Name": "Person", "Confidence": 99.99819946289062, "Instances": [{"BoundingBox": {"Width": 0.6866482496261597, "Height": 0.7380279898643494, "Left": 0.2704584002494812, "Top": 0.2048477679491043}, "Confidence": 96.78987121582031}], "Parents": [], "Aliases": [{"Name": "Human"}], "Categories": [{"Name": "Person Description"}]}, {"Name": "Photography", "Confidence": 99.18362426757812, "Instances": [], "Parents": [], "Aliases": [{"Name": "Photo"}], "Categories": [{"Name": "Hobbies and Interests"}]}, {"Name": "Adult", "Confidence": 96.78987121582031, "Instances": [{"BoundingBox": {"Width": 0.6866482496261597, "Height": 0.7380279898643494, "Left": 0.2704584002494812, "Top": 0.2048477679491043}, "Confidence": 96.78987121582031}], "Parents": [{"Name": "Person"}], "Aliases": [], "Categories": [{"Name": "Person Description"}]}, {"Name": "Male", "Confidence": 96.78987121582031, "Instances": [{"BoundingBox": {"Width": 0.6866482496261597, "Height": 0.7380279898643494, "Left": 0.2704584002494812, "Top": 0.2048477679491043}, "Confidence": 96.78987121582031}], "Parents": [{"Name": "Person"}], "Aliases": [], "Categories": [{"Name": "Person Description"}]}, {"Name": "Man", "Confidence": 96.78987121582031, "Instances": [{"BoundingBox": {"Width": 0.6866482496261597, "Height": 0.7380279898643494, "Left": 0.2704584002494812, "Top": 0.2048477679491043}, "Confidence": 96.78987121582031}], "Parents": [{"Name": "Adult"}, {"Name": "Male"}, {"Name": "Person"}], "Aliases": [], "Categories": [{"Name": "Person Description"}]}, {"Name": "Face", "Confidence": 88.34729766845703, "Instances": [], "Parents": [{"Name": "Head"}, {"Name": "Person"}], "Aliases": [], "Categories": [{"Name": "Person Description"}]}, {"Name": "Head", "Confidence": 88.34729766845703, "Instances": [], "Parents": [{"Name": "Person"}], "Aliases": [], "Categories": [{"Name": "Person Description"}]}, {"Name": "Fashion", "Confidence": 80.66700744628906, "Instances": [], "Parents": [], "Aliases": [], "Categories": [{"Name": "Apparel and Accessories"}]}, {"Name": "Portrait", "Confidence": 57.8963508605957, "Instances": [], "Parents": [{"Name": "Face"}, {"Name": "Head"}, {"Name": "Person"}, {"Name": "Photography"}], "Aliases": [], "Categories": [{"Name": "Hobbies and Interests"}]}, {"Name": "Standing", "Confidence": 57.41488265991211, "Instances": [], "Parents": [{"Name": "Person"}], "Aliases": [], "Categories": [{"Name": "Actions"}]}], "2_google.jpg": [{"Name": "People", "Confidence": 100.0, "Instances": [], "Parents": [{"Name": "Person"}], "Aliases": [], "Categories": [{"Name": "Person Description"}]}, {"Name": "Person", "Confidence": 100.0, "Instances": [{"BoundingBox": {"Width": 0.22563621401786804, "Height": 0.8789998292922974, "Left": 0.0, "Top": 0.11846978962421417}, "Confidence": 99.72577667236328}, {"BoundingBox": {"Width": 0.23134897649288177, "Height": 0.8764275312423706, "Left": 0.7672034502029419, "Top": 0.12207400053739548}, "Confidence": 97.78205108642578}, {"BoundingBox": {"Width": 0.27501600980758667, "Height": 0.9012137651443481, "Left": 0.5018590092658997, "Top": 0.09869943559169769}, "Confidence": 95.31743621826172}, {"BoundingBox": {"Width": 0.3709043860435486, "Height": 0.8912600874900818, "Left": 0.16182947158813477, "Top": 0.10873990505933762}, "Confidence": 95.1317367553711}], "Parents": [], "Aliases": [{"Name": "Human"}], "Categories": [{"Name": "Person Description"}]}, {"Name": "Family", "Confidence": 99.92891693115234, "Instances": [], "Parents": [{"Name": "People"}, {"Name": "Person"}], "Aliases": [], "Categories": [{"Name": "Person Description"}]}, {"Name": "Adult", "Confidence": 99.72577667236328, "Instances": [{"BoundingBox": {"Width": 0.22563621401786804, "Height": 0.8789998292922974, "Left": 0.0, "Top": 0.11846978962421417}, "Confidence": 99.72577667236328}, {"BoundingBox": {"Width": 0.23134897649288177, "Height": 0.8764275312423706, "Left": 0.7672034502029419, "Top": 0.12207400053739548}, "Confidence": 97.78205108642578}, {"BoundingBox": {"Width": 0.27501600980758667, "Height": 0.9012137651443481, "Left": 0.5018590092658997, "Top": 0.09869943559169769}, "Confidence": 95.31743621826172}, {"BoundingBox": {"Width": 0.3709043860435486, "Height": 0.8912600874900818, "Left": 0.16182947158813477, "Top": 0.10873990505933762}, "Confidence": 95.1317367553711}], "Parents": [{"Name": "Person"}], "Aliases": [], "Categories": [{"Name": "Person Description"}]}, {"Name": "Female", "Confidence": 99.72577667236328, "Instances": [{"BoundingBox": {"Width": 0.22563621401786804, "Height": 0.8789998292922974, "Left": 0.0, "Top": 0.11846978962421417}, "Confidence": 99.72577667236328}], "Parents": [{"Name": "Person"}], "Aliases": [], "Categories": [{"Name": "Person Description"}]}, {"Name": "Woman", "Confidence": 99.72577667236328, "Instances": [{"BoundingBox": {"Width": 0.22563621401786804, "Height": 0.8789998292922974, "Left": 0.0, "Top": 0.11846978962421417}, "Confidence": 99.72577667236328}], "Parents": [{"Name": "Adult"}, {"Name": "Female"}, {"Name": "Person"}], "Aliases": [], "Categories": [{"Name": "Person Description"}]}, {"Name": "Male", "Confidence": 97.78205108642578, "Instances": [{"BoundingBox": {"Width": 0.23134897649288177, "Height": 0.8764275312423706, "Left": 0.7672034502029419, "Top": 0.12207400053739548}, "Confidence": 97.78205108642578}, {"BoundingBox": {"Width": 0.27501600980758667, "Height": 0.9012137651443481, "Left": 0.5018590092658997, "Top": 0.09869943559169769}, "Confidence": 95.31743621826172}, {"BoundingBox": {"Width": 0.3709043860435486, "Height": 0.8912600874900818, "Left": 0.16182947158813477, "Top": 0.10873990505933762}, "Confidence": 95.1317367553711}], "Parents": [{"Name": "Person"}], "Aliases": [], "Categories": [{"Name": "Person Description"}]}, {"Name": "Man", "Confidence": 97.78205108642578, "Instances": [{"BoundingBox": {"Width": 0.23134897649288177, "Height": 0.8764275312423706, "Left": 0.7672034502029419, "Top": 0.12207400053739548}, "Confidence": 97.78205108642578}, {"BoundingBox": {"Width": 0.27501600980758667, "Height": 0.9012137651443481, "Left": 0.5018590092658997, "Top": 0.09869943559169769}, "Confidence": 95.31743621826172}, {"BoundingBox": {"Width": 0.3709043860435486, "Height": 0.8912600874900818, "Left": 0.16182947158813477, "Top": 0.10873990505933762}, "Confidence": 95.1317367553711}], "Parents": [{"Name": "Adult"}, {"Name": "Male"}, {"Name": "Person"}], "Aliases": [], "Categories": [{"Name": "Person Description"}]}, {"Name": "Head", "Confidence": 94.68358612060547, "Instances": [], "Parents": [{"Name": "Person"}], "Aliases": [], "Categories": [{"Name": "Person Description"}]}, {"Name": "Face", "Confidence": 93.5329818725586, "Instances": [], "Parents": [{"Name": "Head"}, {"Name": "Person"}], "Aliases": [], "Categories": [{"Name": "Person Description"}]}, {"Name": "Clothing", "Confidence": 70.28788757324219, "Instances": [], "Parents": [], "Aliases": [{"Name": "Apparel"}], "Categories": [{"Name": "Apparel and Accessories"}]}, {"Name": "Coat", "Confidence": 70.28788757324219, "Instances": [{"BoundingBox": {"Width": 0.17645935714244843, "Height": 0.4972364902496338, "Left": 0.34872716665267944, "Top": 0.5010689496994019}, "Confidence": 70.28788757324219}], "Parents": [{"Name": "Clothing"}], "Aliases": [], "Categories": [{"Name": "Apparel and Accessories"}]}, {"Name": "Groupshot", "Confidence": 55.28717803955078, "Instances": [], "Parents": [{"Name": "Person"}], "Aliases": [], "Categories": [{"Name": "Colors and Visual Composition"}]}], "3_google.jpg": [{"Name": "Accessories", "Confidence": 100.0, "Instances": [], "Parents": [], "Aliases": [{"Name": "Accessory"}], "Categories": [{"Name": "Apparel and Accessories"}]}, {"Name": "Formal Wear", "Confidence": 100.0, "Instances": [], "Parents": [], "Aliases": [], "Categories": [{"Name": "Apparel and Accessories"}]}, {"Name": "Tie", "Confidence": 100.0, "Instances": [{"BoundingBox": {"Width": 0.23718200623989105, "Height": 0.3875690698623657, "Left": 0.34295016527175903, "Top": 0.6104916930198669}, "Confidence": 99.4146499633789}], "Parents": [{"Name": "Accessories"}, {"Name": "Formal Wear"}], "Aliases": [], "Categories": [{"Name": "Apparel and Accessories"}]}, {"Name": "Clothing", "Confidence": 99.99876403808594, "Instances": [], "Parents": [], "Aliases": [{"Name": "Apparel"}], "Categories": [{"Name": "Apparel and Accessories"}]}, {"Name": "Shirt", "Confidence": 99.99876403808594, "Instances": [{"BoundingBox": {"Width": 0.9978851079940796, "Height": 0.5085176229476929, "Left": 0.0003200531064067036, "Top": 0.488981693983078}, "Confidence": 99.80738067626953}], "Parents": [{"Name": "Clothing"}], "Aliases": [], "Categories": [{"Name": "Apparel and Accessories"}]}, {"Name": "Necktie", "Confidence": 99.99635314941406, "Instances": [], "Parents": [{"Name": "Accessories"}, {"Name": "Formal Wear"}, {"Name": "Tie"}], "Aliases": [], "Categories": [{"Name": "Apparel and Accessories"}]}, {"Name": "Adult", "Confidence": 98.84326171875, "Instances": [{"BoundingBox": {"Width": 0.9960895776748657, "Height": 0.8888125419616699, "Left": 0.0006453704554587603, "Top": 0.1059664711356163}, "Confidence": 98.84326171875}], "Parents": [{"Name": "Person"}], "Aliases": [], "Categories": [{"Name": "Person Description"}]}, {"Name": "Male", "Confidence": 98.84326171875, "Instances": [{"BoundingBox": {"Width": 0.9960895776748657, "Height": 0.8888125419616699, "Left": 0.0006453704554587603, "Top": 0.1059664711356163}, "Confidence": 98.84326171875}], "Parents": [{"Name": "Person"}], "Aliases": [], "Categories": [{"Name": "Person Description"}]}, {"Name": "Man", "Confidence": 98.84326171875, "Instances": [{"BoundingBox": {"Width": 0.9960895776748657, "Height": 0.8888125419616699, "Left": 0.0006453704554587603, "Top": 0.1059664711356163}, "Confidence": 98.84326171875}], "Parents": [{"Name": "Adult"}, {"Name": "Male"}, {"Name": "Person"}], "Aliases": [], "Categories": [{"Name": "Person Description"}]}, {"Name": "Person", "Confidence": 98.84326171875, "Instances": [{"BoundingBox": {"Width": 0.9960895776748657, "Height": 0.8888125419616699, "Left": 0.0006453704554587603, "Top": 0.1059664711356163}, "Confidence": 98.84326171875}], "Parents": [], "Aliases": [{"Name": "Human"}], "Categories": [{"Name": "Person Description"}]}, {"Name": "Face", "Confidence": 93.18263244628906, "Instances": [], "Parents": [{"Name": "Head"}, {"Name": "Person"}], "Aliases": [], "Categories": [{"Name": "Person Description"}]}, {"Name": "Head", "Confidence": 93.18263244628906, "Instances": [], "Parents": [{"Name": "Person"}], "Aliases": [], "Categories": [{"Name": "Person Description"}]}, {"Name": "Dress Shirt", "Confidence": 56.72290802001953, "Instances": [], "Parents": [{"Name": "Clothing"}, {"Name": "Shirt"}], "Aliases": [], "Categories": [{"Name": "Apparel and Accessories"}]}, {"Name": "Photography", "Confidence": 56.539146423339844, "Instances": [], "Parents": [], "Aliases": [{"Name": "Photo"}], "Categories": [{"Name": "Hobbies and Interests"}]}, {"Name": "Portrait", "Confidence": 56.539146423339844, "Instances": [], "Parents": [{"Name": "Face"}, {"Name": "Head"}, {"Name": "Person"}, {"Name": "Photography"}], "Aliases": [], "Categories": [{"Name": "Hobbies and Interests"}]}, {"Name": "Suit", "Confidence": 55.85066223144531, "Instances": [], "Parents": [{"Name": "Clothing"}, {"Name": "Formal Wear"}], "Aliases": [], "Categories": [{"Name": "Apparel and Accessories"}]}], "4_google.jpg": [{"Name": "People", "Confidence": 99.99701690673828, "Instances": [], "Parents": [{"Name": "Person"}], "Aliases": [], "Categories": [{"Name": "Person Description"}]}, {"Name": "Person", "Confidence": 99.99701690673828, "Instances": [{"BoundingBox": {"Width": 0.267082542181015, "Height": 0.8960072994232178, "Left": 0.7140399813652039, "Top": 0.04507293552160263}, "Confidence": 98.8188705444336}, {"BoundingBox": {"Width": 0.2892538607120514, "Height": 0.911686360836029, "Left": 0.24293389916419983, "Top": 0.042800258845090866}, "Confidence": 98.76495361328125}, {"BoundingBox": {"Width": 0.2801302671432495, "Height": 0.9147224426269531, "Left": 0.008451814763247967, "Top": 0.03372917324304581}, "Confidence": 98.68402099609375}, {"BoundingBox": {"Width": 0.2599245309829712, "Height": 0.8973466753959656, "Left": 0.49394771456718445, "Top": 0.04536018520593643}, "Confidence": 98.36354064941406}], "Parents": [], "Aliases": [{"Name": "Human"}], "Categories": [{"Name": "Person Description"}]}, {"Name": "Fashion", "Confidence": 99.99537658691406, "Instances": [], "Parents": [], "Aliases": [], "Categories": [{"Name": "Apparel and Accessories"}]}, {"Name": "Adult", "Confidence": 98.8188705444336, "Instances": [{"BoundingBox": {"Width": 0.267082542181015, "Height": 0.8960072994232178, "Left": 0.7140399813652039, "Top": 0.04507293552160263}, "Confidence": 98.8188705444336}, {"BoundingBox": {"Width": 0.2892538607120514, "Height": 0.911686360836029, "Left": 0.24293389916419983, "Top": 0.042800258845090866}, "Confidence": 98.76495361328125}, {"BoundingBox": {"Width": 0.2801302671432495, "Height": 0.9147224426269531, "Left": 0.008451814763247967, "Top": 0.03372917324304581}, "Confidence": 98.68402099609375}, {"BoundingBox": {"Width": 0.2599245309829712, "Height": 0.8973466753959656, "Left": 0.49394771456718445, "Top": 0.04536018520593643}, "Confidence": 98.36354064941406}], "Parents": [{"Name": "Person"}], "Aliases": [], "Categories": [{"Name": "Person Description"}]}, {"Name": "Male", "Confidence": 98.8188705444336, "Instances": [{"BoundingBox": {"Width": 0.267082542181015, "Height": 0.8960072994232178, "Left": 0.7140399813652039, "Top": 0.04507293552160263}, "Confidence": 98.8188705444336}, {"BoundingBox": {"Width": 0.2892538607120514, "Height": 0.911686360836029, "Left": 0.24293389916419983, "Top": 0.042800258845090866}, "Confidence": 98.76495361328125}, {"BoundingBox": {"Width": 0.2801302671432495, "Height": 0.9147224426269531, "Left": 0.008451814763247967, "Top": 0.03372917324304581}, "Confidence": 98.68402099609375}, {"BoundingBox": {"Width": 0.2599245309829712, "Height": 0.8973466753959656, "Left": 0.49394771456718445, "Top": 0.04536018520593643}, "Confidence": 98.36354064941406}], "Parents": [{"Name": "Person"}], "Aliases": [], "Categories": [{"Name": "Person Description"}]}, {"Name": "Man", "Confidence": 98.8188705444336, "Instances": [{"BoundingBox": {"Width": 0.267082542181015, "Height": 0.8960072994232178, "Left": 0.7140399813652039, "Top": 0.04507293552160263}, "Confidence": 98.8188705444336}, {"BoundingBox": {"Width": 0.2892538607120514, "Height": 0.911686360836029, "Left": 0.24293389916419983, "Top": 0.042800258845090866}, "Confidence": 98.76495361328125}, {"BoundingBox": {"Width": 0.2801302671432495, "Height": 0.9147224426269531, "Left": 0.008451814763247967, "Top": 0.03372917324304581}, "Confidence": 98.68402099609375}, {"BoundingBox": {"Width": 0.2599245309829712, "Height": 0.8973466753959656, "Left": 0.49394771456718445, "Top": 0.04536018520593643}, "Confidence": 98.36354064941406}], "Parents": [{"Name": "Adult"}, {"Name": "Male"}, {"Name": "Person"}], "Aliases": [], "Categories": [{"Name": "Person Description"}]}, {"Name": "Clothing", "Confidence": 89.23060607910156, "Instances": [], "Parents": [], "Aliases": [{"Name": "Apparel"}], "Categories": [{"Name": "Apparel and Accessories"}]}, {"Name": "Footwear", "Confidence": 89.23060607910156, "Instances": [], "Parents": [{"Name": "Clothing"}], "Aliases": [], "Categories": [{"Name": "Apparel and Accessories"}]}, {"Name": "Shoe", "Confidence": 89.23060607910156, "Instances": [{"BoundingBox": {"Width": 0.058517906814813614, "Height": 0.04512924328446388, "Left": 0.6189844012260437, "Top": 0.8956589698791504}, "Confidence": 89.23060607910156}, {"BoundingBox": {"Width": 0.09869203716516495, "Height": 0.05121136084198952, "Left": 0.7483201622962952, "Top": 0.8828735947608948}, "Confidence": 84.13556671142578}, {"BoundingBox": {"Width": 0.06587740778923035, "Height": 0.04438265413045883, "Left": 0.15224972367286682, "Top": 0.900454044342041}, "Confidence": 81.00188446044922}, {"BoundingBox": {"Width": 0.09566958993673325, "Height": 0.046088702976703644, "Left": 0.8873157501220703, "Top": 0.8973761796951294}, "Confidence": 79.15669250488281}, {"BoundingBox": {"Width": 0.10355247557163239, "Height": 0.06263721734285355, "Left": 0.4900828003883362, "Top": 0.8791126608848572}, "Confidence": 73.14059448242188}, {"BoundingBox": {"Width": 0.05292942374944687, "Height": 0.04047444835305214, "Left": 0.06779469549655914, "Top": 0.8846597075462341}, "Confidence": 72.51687622070312}, {"BoundingBox": {"Width": 0.04369981586933136, "Height": 0.0634494349360466, "Left": 0.3237912058830261, "Top": 0.8492477536201477}, "Confidence": 72.3499755859375}, {"BoundingBox": {"Width": 0.08070023357868195, "Height": 0.05782485753297806, "Left": 0.3903122544288635, "Top": 0.8982104659080505}, "Confidence": 68.63699340820312}], "Parents": [{"Name": "Clothing"}, {"Name": "Footwear"}], "Aliases": [], "Categories": [{"Name": "Apparel and Accessories"}]}, {"Name": "Face", "Confidence": 68.67282104492188, "Instances": [], "Parents": [{"Name": "Head"}, {"Name": "Person"}], "Aliases": [], "Categories": [{"Name": "Person Description"}]}, {"Name": "Robe", "Confidence": 61.962425231933594, "Instances": [], "Parents": [{"Name": "Clothing"}, {"Name": "Fashion"}], "Aliases": [], "Categories": [{"Name": "Apparel and Accessories"}]}, {"Name": "Laptop", "Confidence": 59.50332260131836, "Instances": [{"BoundingBox": {"Width": 0.13292236626148224, "Height": 0.10645322501659393, "Left": 0.7824915051460266, "Top": 0.40604010224342346}, "Confidence": 59.50332260131836}], "Parents": [{"Name": "Computer"}, {"Name": "Electronics"}, {"Name": "Pc"}], "Aliases": [], "Categories": [{"Name": "Technology and Computing"}]}, {"Name": "Pc", "Confidence": 59.50332260131836, "Instances": [], "Parents": [{"Name": "Computer"}, {"Name": "Electronics"}], "Aliases": [], "Categories": [{"Name": "Technology and Computing"}]}, {"Name": "Long Sleeve", "Confidence": 57.00685501098633, "Instances": [], "Parents": [{"Name": "Clothing"}, {"Name": "Sleeve"}], "Aliases": [], "Categories": [{"Name": "Apparel and Accessories"}]}, {"Name": "Sleeve", "Confidence": 57.00685501098633, "Instances": [], "Parents": [{"Name": "Clothing"}], "Aliases": [], "Categories": [{"Name": "Apparel and Accessories"}]}, {"Name": "Dress", "Confidence": 56.1619758605957, "Instances": [], "Parents": [{"Name": "Clothing"}], "Aliases": [], "Categories": [{"Name": "Apparel and Accessories"}]}, {"Name": "Standing", "Confidence": 55.94784164428711, "Instances": [], "Parents": [{"Name": "Person"}], "Aliases": [], "Categories": [{"Name": "Actions"}]}, {"Name": "Cloak", "Confidence": 55.35292053222656, "Instances": [], "Parents": [{"Name": "Clothing"}, {"Name": "Fashion"}], "Aliases": [], "Categories": [{"Name": "Apparel and Accessories"}]}, {"Name": "Building", "Confidence": 55.33899688720703, "Instances": [], "Parents": [{"Name": "Architecture"}], "Aliases": [], "Categories": [{"Name": "Buildings and Architecture"}]}, {"Name": "Hospital", "Confidence": 55.33899688720703, "Instances": [], "Parents": [{"Name": "Architecture"}, {"Name": "Building"}], "Aliases": [], "Categories": [{"Name": "Medical"}]}], "5_google.jpg": [{"Name": "Clothing", "Confidence": 99.99876403808594, "Instances": [], "Parents": [], "Aliases": [{"Name": "Apparel"}], "Categories": [{"Name": "Apparel and Accessories"}]}, {"Name": "Coat", "Confidence": 99.99876403808594, "Instances": [{"BoundingBox": {"Width": 0.3034878075122833, "Height": 0.5942347645759583, "Left": 0.012756395153701305, "Top": 0.1690090149641037}, "Confidence": 99.30500030517578}, {"BoundingBox": {"Width": 0.30698686838150024, "Height": 0.6177687048912048, "Left": 0.6911572813987732, "Top": 0.15848344564437866}, "Confidence": 95.9674072265625}, {"BoundingBox": {"Width": 0.32899242639541626, "Height": 0.6278478503227234, "Left": 0.42587029933929443, "Top": 0.14042970538139343}, "Confidence": 93.6565170288086}], "Parents": [{"Name": "Clothing"}], "Aliases": [], "Categories": [{"Name": "Apparel and Accessories"}]}, {"Name": "People", "Confidence": 99.99854278564453, "Instances": [], "Parents": [{"Name": "Person"}], "Aliases": [], "Categories": [{"Name": "Person Description"}]}, {"Name": "Person", "Confidence": 99.99854278564453, "Instances": [{"BoundingBox": {"Width": 0.3024963140487671, "Height": 0.8776947259902954, "Left": 0.013575935736298561, "Top": 0.05216529965400696}, "Confidence": 98.73208618164062}, {"BoundingBox": {"Width": 0.30893370509147644, "Height": 0.8953927159309387, "Left": 0.6875779032707214, "Top": 0.04352390393614769}, "Confidence": 97.52113342285156}, {"BoundingBox": {"Width": 0.25656360387802124, "Height": 0.8915305733680725, "Left": 0.28103113174438477, "Top": 0.0366966612637043}, "Confidence": 97.23980712890625}, {"BoundingBox": {"Width": 0.3286868929862976, "Height": 0.842673122882843, "Left": 0.4232710003852844, "Top": 0.044355202466249466}, "Confidence": 97.06488037109375}], "Parents": [], "Aliases": [{"Name": "Human"}], "Categories": [{"Name": "Person Description"}]}, {"Name": "Fashion", "Confidence": 99.34107971191406, "Instances": [], "Parents": [], "Aliases": [], "Categories": [{"Name": "Apparel and Accessories"}]}, {"Name": "Adult", "Confidence": 98.73208618164062, "Instances": [{"BoundingBox": {"Width": 0.3024963140487671, "Height": 0.8776947259902954, "Left": 0.013575935736298561, "Top": 0.05216529965400696}, "Confidence": 98.73208618164062}, {"BoundingBox": {"Width": 0.30893370509147644, "Height": 0.8953927159309387, "Left": 0.6875779032707214, "Top": 0.04352390393614769}, "Confidence": 97.52113342285156}, {"BoundingBox": {"Width": 0.25656360387802124, "Height": 0.8915305733680725, "Left": 0.28103113174438477, "Top": 0.0366966612637043}, "Confidence": 97.23980712890625}, {"BoundingBox": {"Width": 0.3286868929862976, "Height": 0.842673122882843, "Left": 0.4232710003852844, "Top": 0.044355202466249466}, "Confidence": 97.06488037109375}], "Parents": [{"Name": "Person"}], "Aliases": [], "Categories": [{"Name": "Person Description"}]}, {"Name": "Male", "Confidence": 98.73208618164062, "Instances": [{"BoundingBox": {"Width": 0.3024963140487671, "Height": 0.8776947259902954, "Left": 0.013575935736298561, "Top": 0.05216529965400696}, "Confidence": 98.73208618164062}, {"BoundingBox": {"Width": 0.30893370509147644, "Height": 0.8953927159309387, "Left": 0.6875779032707214, "Top": 0.04352390393614769}, "Confidence": 97.52113342285156}, {"BoundingBox": {"Width": 0.25656360387802124, "Height": 0.8915305733680725, "Left": 0.28103113174438477, "Top": 0.0366966612637043}, "Confidence": 97.23980712890625}, {"BoundingBox": {"Width": 0.3286868929862976, "Height": 0.842673122882843, "Left": 0.4232710003852844, "Top": 0.044355202466249466}, "Confidence": 97.06488037109375}], "Parents": [{"Name": "Person"}], "Aliases": [], "Categories": [{"Name": "Person Description"}]}, {"Name": "Man", "Confidence": 98.73208618164062, "Instances": [{"BoundingBox": {"Width": 0.3024963140487671, "Height": 0.8776947259902954, "Left": 0.013575935736298561, "Top": 0.05216529965400696}, "Confidence": 98.73208618164062}, {"BoundingBox": {"Width": 0.30893370509147644, "Height": 0.8953927159309387, "Left": 0.6875779032707214, "Top": 0.04352390393614769}, "Confidence": 97.52113342285156}, {"BoundingBox": {"Width": 0.25656360387802124, "Height": 0.8915305733680725, "Left": 0.28103113174438477, "Top": 0.0366966612637043}, "Confidence": 97.23980712890625}, {"BoundingBox": {"Width": 0.3286868929862976, "Height": 0.842673122882843, "Left": 0.4232710003852844, "Top": 0.044355202466249466}, "Confidence": 97.06488037109375}], "Parents": [{"Name": "Adult"}, {"Name": "Male"}, {"Name": "Person"}], "Aliases": [], "Categories": [{"Name": "Person Description"}]}, {"Name": "Footwear", "Confidence": 85.8801040649414, "Instances": [], "Parents": [{"Name": "Clothing"}], "Aliases": [], "Categories": [{"Name": "Apparel and Accessories"}]}, {"Name": "Shoe", "Confidence": 85.8801040649414, "Instances": [{"BoundingBox": {"Width": 0.12765875458717346, "Height": 0.06333404779434204, "Left": 0.28078731894493103, "Top": 0.8577226996421814}, "Confidence": 85.8801040649414}, {"BoundingBox": {"Width": 0.10469140857458115, "Height": 0.05638366565108299, "Left": 0.5561395287513733, "Top": 0.8749426603317261}, "Confidence": 78.14994812011719}, {"BoundingBox": {"Width": 0.07417602837085724, "Height": 0.05176354944705963, "Left": 0.20193172991275787, "Top": 0.8767686486244202}, "Confidence": 74.3202133178711}, {"BoundingBox": {"Width": 0.09379822015762329, "Height": 0.05118804797530174, "Left": 0.392846018075943, "Top": 0.8744733333587646}, "Confidence": 72.88893127441406}, {"BoundingBox": {"Width": 0.057583313435316086, "Height": 0.04794128239154816, "Left": 0.8579403758049011, "Top": 0.8850700855255127}, "Confidence": 67.04032897949219}, {"BoundingBox": {"Width": 0.06669183075428009, "Height": 0.05133398622274399, "Left": 0.12596462666988373, "Top": 0.8613172769546509}, "Confidence": 66.02580261230469}, {"BoundingBox": {"Width": 0.09868994355201721, "Height": 0.06646227836608887, "Left": 0.7290211319923401, "Top": 0.8728216290473938}, "Confidence": 56.57037353515625}], "Parents": [{"Name": "Clothing"}, {"Name": "Footwear"}], "Aliases": [], "Categories": [{"Name": "Apparel and Accessories"}]}, {"Name": "Face", "Confidence": 74.79666900634766, "Instances": [], "Parents": [{"Name": "Head"}, {"Name": "Person"}], "Aliases": [], "Categories": [{"Name": "Person Description"}]}, {"Name": "Head", "Confidence": 74.79666900634766, "Instances": [], "Parents": [{"Name": "Person"}], "Aliases": [], "Categories": [{"Name": "Person Description"}]}, {"Name": "Standing", "Confidence": 55.611671447753906, "Instances": [], "Parents": [{"Name": "Person"}], "Aliases": [], "Categories": [{"Name": "Actions"}]}, {"Name": "Shirt", "Confidence": 55.429874420166016, "Instances": [], "Parents": [{"Name": "Clothing"}], "Aliases": [], "Categories": [{"Name": "Apparel and Accessories"}]}], "6_google.jpg": [{"Name": "Clothing", "Confidence": 99.99993133544922, "Instances": [], "Parents": [], "Aliases": [{"Name": "Apparel"}], "Categories": [{"Name": "Apparel and Accessories"}]}, {"Name": "Coat", "Confidence": 99.99993133544922, "Instances": [{"BoundingBox": {"Width": 0.396281361579895, "Height": 0.5980667471885681, "Left": 0.30964526534080505, "Top": 0.1962210088968277}, "Confidence": 93.85671997070312}], "Parents": [{"Name": "Clothing"}], "Aliases": [], "Categories": [{"Name": "Apparel and Accessories"}]}, {"Name": "Lab Coat", "Confidence": 99.99105834960938, "Instances": [], "Parents": [{"Name": "Clothing"}, {"Name": "Coat"}], "Aliases": [], "Categories": [{"Name": "Apparel and Accessories"}]}, {"Name": "Adult", "Confidence": 99.4441909790039, "Instances": [{"BoundingBox": {"Width": 0.39595234394073486, "Height": 0.8918976187705994, "Left": 0.30911150574684143, "Top": 0.07179636508226395}, "Confidence": 99.4441909790039}], "Parents": [{"Name": "Person"}], "Aliases": [], "Categories": [{"Name": "Person Description"}]}, {"Name": "Male", "Confidence": 99.4441909790039, "Instances": [{"BoundingBox": {"Width": 0.39595234394073486, "Height": 0.8918976187705994, "Left": 0.30911150574684143, "Top": 0.07179636508226395}, "Confidence": 99.4441909790039}], "Parents": [{"Name": "Person"}], "Aliases": [], "Categories": [{"Name": "Person Description"}]}, {"Name": "Man", "Confidence": 99.4441909790039, "Instances": [{"BoundingBox": {"Width": 0.39595234394073486, "Height": 0.8918976187705994, "Left": 0.30911150574684143, "Top": 0.07179636508226395}, "Confidence": 99.4441909790039}], "Parents": [{"Name": "Adult"}, {"Name": "Male"}, {"Name": "Person"}], "Aliases": [], "Categories": [{"Name": "Person Description"}]}, {"Name": "Person", "Confidence": 99.4441909790039, "Instances": [{"BoundingBox": {"Width": 0.39595234394073486, "Height": 0.8918976187705994, "Left": 0.30911150574684143, "Top": 0.07179636508226395}, "Confidence": 99.4441909790039}], "Parents": [], "Aliases": [{"Name": "Human"}], "Categories": [{"Name": "Person Description"}]}, {"Name": "Standing", "Confidence": 89.00642395019531, "Instances": [], "Parents": [{"Name": "Person"}], "Aliases": [], "Categories": [{"Name": "Actions"}]}, {"Name": "Shirt", "Confidence": 69.95352935791016, "Instances": [], "Parents": [{"Name": "Clothing"}], "Aliases": [], "Categories": [{"Name": "Apparel and Accessories"}]}, {"Name": "Long Sleeve", "Confidence": 56.96396255493164, "Instances": [], "Parents": [{"Name": "Clothing"}, {"Name": "Sleeve"}], "Aliases": [], "Categories": [{"Name": "Apparel and Accessories"}]}, {"Name": "Sleeve", "Confidence": 56.96396255493164, "Instances": [], "Parents": [{"Name": "Clothing"}], "Aliases": [], "Categories": [{"Name": "Apparel and Accessories"}]}, {"Name": "People", "Confidence": 56.60055923461914, "Instances": [], "Parents": [{"Name": "Person"}], "Aliases": [], "Categories": [{"Name": "Person Description"}]}], "7_google.jpg": [{"Name": "Body Part", "Confidence": 99.97038269042969, "Instances": [], "Parents": [], "Aliases": [], "Categories": [{"Name": "Person Description"}]}, {"Name": "Finger", "Confidence": 99.97038269042969, "Instances": [], "Parents": [{"Name": "Body Part"}, {"Name": "Hand"}, {"Name": "Person"}], "Aliases": [], "Categories": [{"Name": "Person Description"}]}, {"Name": "Hand", "Confidence": 99.97038269042969, "Instances": [], "Parents": [{"Name": "Body Part"}, {"Name": "Person"}], "Aliases": [], "Categories": [{"Name": "Person Description"}]}, {"Name": "Person", "Confidence": 99.97038269042969, "Instances": [{"BoundingBox": {"Width": 0.38498151302337646, "Height": 0.8975140452384949, "Left": 0.00010385330097051337, "Top": 0.09828582406044006}, "Confidence": 99.8352279663086}, {"BoundingBox": {"Width": 0.3091078996658325, "Height": 0.8857311010360718, "Left": 0.24498511850833893, "Top": 0.1140294298529625}, "Confidence": 99.80944061279297}, {"BoundingBox": {"Width": 0.5480985045433044, "Height": 0.9937118291854858, "Left": 0.45143091678619385, "Top": 0.004077262710779905}, "Confidence": 98.994873046875}, {"BoundingBox": {"Width": 0.13923737406730652, "Height": 0.2860676348209381, "Left": 0.8590314984321594, "Top": 0.7129905819892883}, "Confidence": 91.90174865722656}, {"BoundingBox": {"Width": 0.19204260408878326, "Height": 0.7403898239135742, "Left": 0.38802823424339294, "Top": 1.6670226614223793e-05}, "Confidence": 90.63336181640625}, {"BoundingBox": {"Width": 0.10061332583427429, "Height": 0.248684823513031, "Left": 0.45604246854782104, "Top": 0.7503513693809509}, "Confidence": 88.07687377929688}], "Parents": [], "Aliases": [{"Name": "Human"}], "Categories": [{"Name": "Person Description"}]}, {"Name": "Adult", "Confidence": 99.8352279663086, "Instances": [{"BoundingBox": {"Width": 0.38498151302337646, "Height": 0.8975140452384949, "Left": 0.00010385330097051337, "Top": 0.09828582406044006}, "Confidence": 99.8352279663086}, {"BoundingBox": {"Width": 0.3091078996658325, "Height": 0.8857311010360718, "Left": 0.24498511850833893, "Top": 0.1140294298529625}, "Confidence": 99.80944061279297}, {"BoundingBox": {"Width": 0.5480985045433044, "Height": 0.9937118291854858, "Left": 0.45143091678619385, "Top": 0.004077262710779905}, "Confidence": 98.994873046875}, {"BoundingBox": {"Width": 0.19204260408878326, "Height": 0.7403898239135742, "Left": 0.38802823424339294, "Top": 1.6670226614223793e-05}, "Confidence": 90.63336181640625}], "Parents": [{"Name": "Person"}], "Aliases": [], "Categories": [{"Name": "Person Description"}]}, {"Name": "Female", "Confidence": 99.8352279663086, "Instances": [{"BoundingBox": {"Width": 0.38498151302337646, "Height": 0.8975140452384949, "Left": 0.00010385330097051337, "Top": 0.09828582406044006}, "Confidence": 99.8352279663086}, {"BoundingBox": {"Width": 0.3091078996658325, "Height": 0.8857311010360718, "Left": 0.24498511850833893, "Top": 0.1140294298529625}, "Confidence": 99.80944061279297}, {"BoundingBox": {"Width": 0.5480985045433044, "Height": 0.9937118291854858, "Left": 0.45143091678619385, "Top": 0.004077262710779905}, "Confidence": 98.994873046875}, {"BoundingBox": {"Width": 0.19204260408878326, "Height": 0.7403898239135742, "Left": 0.38802823424339294, "Top": 1.6670226614223793e-05}, "Confidence": 90.63336181640625}], "Parents": [{"Name": "Person"}], "Aliases": [], "Categories": [{"Name": "Person Description"}]}, {"Name": "Woman", "Confidence": 99.8352279663086, "Instances": [{"BoundingBox": {"Width": 0.38498151302337646, "Height": 0.8975140452384949, "Left": 0.00010385330097051337, "Top": 0.09828582406044006}, "Confidence": 99.8352279663086}, {"BoundingBox": {"Width": 0.3091078996658325, "Height": 0.8857311010360718, "Left": 0.24498511850833893, "Top": 0.1140294298529625}, "Confidence": 99.80944061279297}, {"BoundingBox": {"Width": 0.5480985045433044, "Height": 0.9937118291854858, "Left": 0.45143091678619385, "Top": 0.004077262710779905}, "Confidence": 98.994873046875}, {"BoundingBox": {"Width": 0.19204260408878326, "Height": 0.7403898239135742, "Left": 0.38802823424339294, "Top": 1.6670226614223793e-05}, "Confidence": 90.63336181640625}], "Parents": [{"Name": "Adult"}, {"Name": "Female"}, {"Name": "Person"}], "Aliases": [], "Categories": [{"Name": "Person Description"}]}, {"Name": "People", "Confidence": 98.77806091308594, "Instances": [], "Parents": [{"Name": "Person"}], "Aliases": [], "Categories": [{"Name": "Person Description"}]}, {"Name": "Head", "Confidence": 98.5656509399414, "Instances": [], "Parents": [{"Name": "Person"}], "Aliases": [], "Categories": [{"Name": "Person Description"}]}, {"Name": "Face", "Confidence": 97.85127258300781, "Instances": [], "Parents": [{"Name": "Head"}, {"Name": "Person"}], "Aliases": [], "Categories": [{"Name": "Person Description"}]}, {"Name": "Crying", "Confidence": 95.59837341308594, "Instances": [], "Parents": [{"Name": "Face"}, {"Name": "Head"}, {"Name": "Person"}, {"Name": "Sad"}], "Aliases": [], "Categories": [{"Name": "Expressions and Emotions"}]}, {"Name": "Sad", "Confidence": 95.59837341308594, "Instances": [], "Parents": [{"Name": "Face"}, {"Name": "Head"}, {"Name": "Person"}], "Aliases": [{"Name": "Worried"}], "Categories": [{"Name": "Expressions and Emotions"}]}, {"Name": "Baby", "Confidence": 91.90174865722656, "Instances": [{"BoundingBox": {"Width": 0.13923737406730652, "Height": 0.2860676348209381, "Left": 0.8590314984321594, "Top": 0.7129905819892883}, "Confidence": 91.90174865722656}, {"BoundingBox": {"Width": 0.10061332583427429, "Height": 0.248684823513031, "Left": 0.45604246854782104, "Top": 0.7503513693809509}, "Confidence": 88.07687377929688}], "Parents": [{"Name": "Person"}], "Aliases": [], "Categories": [{"Name": "Person Description"}]}, {"Name": "Prayer", "Confidence": 56.555049896240234, "Instances": [], "Parents": [], "Aliases": [{"Name": "Worship"}], "Categories": [{"Name": "Religion"}]}], "8_google.jpg": [{"Name": "Clothing", "Confidence": 100.0, "Instances": [], "Parents": [], "Aliases": [{"Name": "Apparel"}], "Categories": [{"Name": "Apparel and Accessories"}]}, {"Name": "Coat", "Confidence": 100.0, "Instances": [], "Parents": [{"Name": "Clothing"}], "Aliases": [], "Categories": [{"Name": "Apparel and Accessories"}]}, {"Name": "Lab Coat", "Confidence": 99.99989318847656, "Instances": [], "Parents": [{"Name": "Clothing"}, {"Name": "Coat"}], "Aliases": [], "Categories": [{"Name": "Apparel and Accessories"}]}, {"Name": "Hoodie", "Confidence": 96.04175567626953, "Instances": [{"BoundingBox": {"Width": 0.5338237285614014, "Height": 0.8645680546760559, "Left": 0.21172578632831573, "Top": 0.10994838178157806}, "Confidence": 96.04175567626953}], "Parents": [{"Name": "Clothing"}, {"Name": "Knitwear"}, {"Name": "Sweater"}, {"Name": "Sweatshirt"}], "Aliases": [], "Categories": [{"Name": "Apparel and Accessories"}]}, {"Name": "Knitwear", "Confidence": 96.04175567626953, "Instances": [], "Parents": [{"Name": "Clothing"}], "Aliases": [{"Name": "Knitted Clothes"}], "Categories": [{"Name": "Apparel and Accessories"}]}, {"Name": "Sweater", "Confidence": 96.04175567626953, "Instances": [], "Parents": [{"Name": "Clothing"}, {"Name": "Knitwear"}], "Aliases": [], "Categories": [{"Name": "Apparel and Accessories"}]}, {"Name": "Sweatshirt", "Confidence": 96.04175567626953, "Instances": [], "Parents": [{"Name": "Clothing"}, {"Name": "Knitwear"}, {"Name": "Sweater"}], "Aliases": [], "Categories": [{"Name": "Apparel and Accessories"}]}, {"Name": "Long Sleeve", "Confidence": 57.547386169433594, "Instances": [], "Parents": [{"Name": "Clothing"}, {"Name": "Sleeve"}], "Aliases": [], "Categories": [{"Name": "Apparel and Accessories"}]}, {"Name": "Sleeve", "Confidence": 57.547386169433594, "Instances": [], "Parents": [{"Name": "Clothing"}], "Aliases": [], "Categories": [{"Name": "Apparel and Accessories"}]}, {"Name": "Face", "Confidence": 57.10349655151367, "Instances": [], "Parents": [{"Name": "Head"}, {"Name": "Person"}], "Aliases": [], "Categories": [{"Name": "Person Description"}]}, {"Name": "Head", "Confidence": 57.10349655151367, "Instances": [], "Parents": [{"Name": "Person"}], "Aliases": [], "Categories": [{"Name": "Person Description"}]}, {"Name": "Person", "Confidence": 57.10349655151367, "Instances": [], "Parents": [], "Aliases": [{"Name": "Human"}], "Categories": [{"Name": "Person Description"}]}, {"Name": "Photography", "Confidence": 57.10349655151367, "Instances": [], "Parents": [], "Aliases": [{"Name": "Photo"}], "Categories": [{"Name": "Hobbies and Interests"}]}, {"Name": "Portrait", "Confidence": 57.10349655151367, "Instances": [], "Parents": [{"Name": "Face"}, {"Name": "Head"}, {"Name": "Person"}, {"Name": "Photography"}], "Aliases": [], "Categories": [{"Name": "Hobbies and Interests"}]}], "9_google.jpg": [{"Name": "Face", "Confidence": 99.99980926513672, "Instances": [], "Parents": [{"Name": "Head"}, {"Name": "Person"}], "Aliases": [], "Categories": [{"Name": "Person Description"}]}, {"Name": "Happy", "Confidence": 99.99980926513672, "Instances": [], "Parents": [{"Name": "Face"}, {"Name": "Head"}, {"Name": "Person"}], "Aliases": [], "Categories": [{"Name": "Expressions and Emotions"}]}, {"Name": "Head", "Confidence": 99.99980926513672, "Instances": [], "Parents": [{"Name": "Person"}], "Aliases": [], "Categories": [{"Name": "Person Description"}]}, {"Name": "Person", "Confidence": 99.99980926513672, "Instances": [{"BoundingBox": {"Width": 0.6372119188308716, "Height": 0.9922800660133362, "Left": 0.046186111867427826, "Top": 0.0070471190847456455}, "Confidence": 95.81796264648438}], "Parents": [], "Aliases": [{"Name": "Human"}], "Categories": [{"Name": "Person Description"}]}, {"Name": "Smile", "Confidence": 99.99980926513672, "Instances": [], "Parents": [{"Name": "Face"}, {"Name": "Happy"}, {"Name": "Head"}, {"Name": "Person"}], "Aliases": [], "Categories": [{"Name": "Expressions and Emotions"}]}, {"Name": "Photography", "Confidence": 98.61534881591797, "Instances": [], "Parents": [], "Aliases": [{"Name": "Photo"}], "Categories": [{"Name": "Hobbies and Interests"}]}, {"Name": "Portrait", "Confidence": 98.61534881591797, "Instances": [], "Parents": [{"Name": "Face"}, {"Name": "Head"}, {"Name": "Person"}, {"Name": "Photography"}], "Aliases": [], "Categories": [{"Name": "Hobbies and Interests"}]}, {"Name": "Adult", "Confidence": 95.81796264648438, "Instances": [{"BoundingBox": {"Width": 0.6372119188308716, "Height": 0.9922800660133362, "Left": 0.046186111867427826, "Top": 0.0070471190847456455}, "Confidence": 95.81796264648438}], "Parents": [{"Name": "Person"}], "Aliases": [], "Categories": [{"Name": "Person Description"}]}, {"Name": "Male", "Confidence": 95.81796264648438, "Instances": [{"BoundingBox": {"Width": 0.6372119188308716, "Height": 0.9922800660133362, "Left": 0.046186111867427826, "Top": 0.0070471190847456455}, "Confidence": 95.81796264648438}], "Parents": [{"Name": "Person"}], "Aliases": [], "Categories": [{"Name": "Person Description"}]}, {"Name": "Man", "Confidence": 95.81796264648438, "Instances": [{"BoundingBox": {"Width": 0.6372119188308716, "Height": 0.9922800660133362, "Left": 0.046186111867427826, "Top": 0.0070471190847456455}, "Confidence": 95.81796264648438}], "Parents": [{"Name": "Adult"}, {"Name": "Male"}, {"Name": "Person"}], "Aliases": [], "Categories": [{"Name": "Person Description"}]}, {"Name": "Dimples", "Confidence": 94.31175994873047, "Instances": [], "Parents": [{"Name": "Face"}, {"Name": "Head"}, {"Name": "Person"}], "Aliases": [], "Categories": [{"Name": "Person Description"}]}, {"Name": "Clothing", "Confidence": 93.63494873046875, "Instances": [], "Parents": [], "Aliases": [{"Name": "Apparel"}], "Categories": [{"Name": "Apparel and Accessories"}]}, {"Name": "Coat", "Confidence": 93.63494873046875, "Instances": [{"BoundingBox": {"Width": 0.6349391937255859, "Height": 0.5538068413734436, "Left": 0.04751481115818024, "Top": 0.444704532623291}, "Confidence": 93.63494873046875}], "Parents": [{"Name": "Clothing"}], "Aliases": [], "Categories": [{"Name": "Apparel and Accessories"}]}, {"Name": "Body Part", "Confidence": 64.24286651611328, "Instances": [], "Parents": [], "Aliases": [], "Categories": [{"Name": "Person Description"}]}, {"Name": "Neck", "Confidence": 64.24286651611328, "Instances": [], "Parents": [{"Name": "Body Part"}, {"Name": "Face"}, {"Name": "Head"}, {"Name": "Person"}], "Aliases": [], "Categories": [{"Name": "Person Description"}]}, {"Name": "Shirt", "Confidence": 57.9747200012207, "Instances": [], "Parents": [{"Name": "Clothing"}], "Aliases": [], "Categories": [{"Name": "Apparel and Accessories"}]}, {"Name": "Black Hair", "Confidence": 56.002933502197266, "Instances": [], "Parents": [{"Name": "Hair"}, {"Name": "Person"}], "Aliases": [], "Categories": [{"Name": "Beauty and Personal Care"}]}, {"Name": "Hair", "Confidence": 56.002933502197266, "Instances": [], "Parents": [{"Name": "Person"}], "Aliases": [], "Categories": [{"Name": "Beauty and Personal Care"}]}]}