{"experiments/valence/pleasant-1/baby1_cifar.png": [{"Name": "Baby", "Confidence": 93.06500244140625, "Instances": [{"BoundingBox": {"Width": 0.8952770829200745, "Height": 0.8874648213386536, "Left": 0.03277946263551712, "Top": 0.07904624938964844}, "Confidence": 93.06500244140625}], "Parents": [{"Name": "Person"}], "Aliases": [], "Categories": [{"Name": "Person Description"}]}, {"Name": "Person", "Confidence": 93.06500244140625, "Instances": [{"BoundingBox": {"Width": 0.8952770829200745, "Height": 0.8874648213386536, "Left": 0.03277946263551712, "Top": 0.07904624938964844}, "Confidence": 93.06500244140625}], "Parents": [], "Aliases": [{"Name": "Human"}], "Categories": [{"Name": "Person Description"}]}, {"Name": "Crawling", "Confidence": 74.53102111816406, "Instances": [], "Parents": [{"Name": "Person"}], "Aliases": [], "Categories": [{"Name": "Actions"}]}], "experiments/valence/pleasant-1/beach1_cifar.png": [{"Name": "Beach", "Confidence": 99.99813079833984, "Instances": [], "Parents": [{"Name": "Coast"}, {"Name": "Nature"}, {"Name": "Outdoors"}, {"Name": "Sea"}, {"Name": "Shoreline"}, {"Name": "Water"}], "Aliases": [], "Categories": [{"Name": "Nature and Outdoors"}]}, {"Name": "Coast", "Confidence": 99.99813079833984, "Instances": [], "Parents": [{"Name": "Nature"}, {"Name": "Outdoors"}, {"Name": "Sea"}, {"Name": "Shoreline"}, {"Name": "Water"}], "Aliases": [], "Categories": [{"Name": "Nature and Outdoors"}]}, {"Name": "Nature", "Confidence": 99.99813079833984, "Instances": [], "Parents": [{"Name": "Outdoors"}], "Aliases": [], "Categories": [{"Name": "Nature and Outdoors"}]}, {"Name": "Outdoors", "Confidence": 99.99813079833984, "Instances": [], "Parents": [], "Aliases": [], "Categories": [{"Name": "Nature and Outdoors"}]}, {"Name": "Sea", "Confidence": 99.99813079833984, "Instances": [], "Parents": [{"Name": "Nature"}, {"Name": "Outdoors"}, {"Name": "Water"}], "Aliases": [{"Name": "Ocean"}], "Categories": [{"Name": "Nature and Outdoors"}]}, {"Name": "Shoreline", "Confidence": 99.99813079833984, "Instances": [], "Parents": [{"Name": "Water"}], "Aliases": [], "Categories": [{"Name": "Nature and Outdoors"}]}, {"Name": "Water", "Confidence": 99.99813079833984, "Instances": [], "Parents": [], "Aliases": [], "Categories": [{"Name": "Nature and Outdoors"}]}, {"Name": "Sky", "Confidence": 99.99737548828125, "Instances": [], "Parents": [{"Name": "Nature"}, {"Name": "Outdoors"}], "Aliases": [], "Categories": [{"Name": "Nature and Outdoors"}]}, {"Name": "Horizon", "Confidence": 98.1143569946289, "Instances": [], "Parents": [{"Name": "Nature"}, {"Name": "Outdoors"}, {"Name": "Sky"}], "Aliases": [], "Categories": [{"Name": "Nature and Outdoors"}]}, {"Name": "Scenery", "Confidence": 96.35592651367188, "Instances": [], "Parents": [{"Name": "Nature"}, {"Name": "Outdoors"}], "Aliases": [], "Categories": [{"Name": "Nature and Outdoors"}]}, {"Name": "Landscape", "Confidence": 56.60272979736328, "Instances": [], "Parents": [{"Name": "Nature"}, {"Name": "Outdoors"}], "Aliases": [], "Categories": [{"Name": "Nature and Outdoors"}]}, {"Name": "Boat", "Confidence": 55.259735107421875, "Instances": [], "Parents": [{"Name": "Transportation"}, {"Name": "Vehicle"}], "Aliases": [], "Categories": [{"Name": "Vehicles and Automotive"}]}, {"Name": "Sailboat", "Confidence": 55.259735107421875, "Instances": [], "Parents": [{"Name": "Boat"}, {"Name": "Transportation"}, {"Name": "Vehicle"}], "Aliases": [], "Categories": [{"Name": "Vehicles and Automotive"}]}, {"Name": "Transportation", "Confidence": 55.259735107421875, "Instances": [], "Parents": [], "Aliases": [], "Categories": [{"Name": "Vehicles and Automotive"}]}, {"Name": "Vehicle", "Confidence": 55.259735107421875, "Instances": [], "Parents": [{"Name": "Transportation"}], "Aliases": [], "Categories": [{"Name": "Vehicles and Automotive"}]}], "experiments/valence/pleasant-1/butterfly1_google.jpg": [{"Name": "Animal", "Confidence": 98.40255737304688, "Instances": [], "Parents": [], "Aliases": [], "Categories": [{"Name": "Animals and Pets"}]}, {"Name": "Butterfly", "Confidence": 98.40255737304688, "Instances": [], "Parents": [{"Name": "Animal"}, {"Name": "Insect"}, {"Name": "Invertebrate"}], "Aliases": [], "Categories": [{"Name": "Animals and Pets"}]}, {"Name": "Insect", "Confidence": 98.40255737304688, "Instances": [], "Parents": [{"Name": "Animal"}, {"Name": "Invertebrate"}], "Aliases": [], "Categories": [{"Name": "Animals and Pets"}]}, {"Name": "Invertebrate", "Confidence": 98.40255737304688, "Instances": [], "Parents": [{"Name": "Animal"}], "Aliases": [], "Categories": [{"Name": "Animals and Pets"}]}, {"Name": "Monarch", "Confidence": 98.40255737304688, "Instances": [], "Parents": [{"Name": "Animal"}, {"Name": "Butterfly"}, {"Name": "Insect"}, {"Name": "Invertebrate"}], "Aliases": [], "Categories": [{"Name": "Animals and Pets"}]}, {"Name": "Appliance", "Confidence": 93.99188232421875, "Instances": [], "Parents": [{"Name": "Device"}, {"Name": "Electrical Device"}], "Aliases": [], "Categories": [{"Name": "Home Appliances"}]}, {"Name": "Ceiling Fan", "Confidence": 93.99188232421875, "Instances": [{"BoundingBox": {"Width": 0.693568766117096, "Height": 0.8375784158706665, "Left": 0.15573866665363312, "Top": 0.014379465952515602}, "Confidence": 93.99188232421875}], "Parents": [{"Name": "Appliance"}, {"Name": "Device"}, {"Name": "Electrical Device"}], "Aliases": [], "Categories": [{"Name": "Furniture and Furnishings"}]}, {"Name": "Device", "Confidence": 93.99188232421875, "Instances": [], "Parents": [], "Aliases": [], "Categories": [{"Name": "Technology and Computing"}]}, {"Name": "Electrical Device", "Confidence": 93.99188232421875, "Instances": [], "Parents": [], "Aliases": [], "Categories": [{"Name": "Technology and Computing"}]}], "experiments/valence/pleasant-1/diamond1_google.png": [{"Name": "Accessories", "Confidence": 100.0, "Instances": [], "Parents": [], "Aliases": [{"Name": "Accessory"}], "Categories": [{"Name": "Apparel and Accessories"}]}, {"Name": "Diamond", "Confidence": 100.0, "Instances": [{"BoundingBox": {"Width": 0.5858798027038574, "Height": 0.5391960740089417, "Left": 0.1995338797569275, "Top": 0.19276784360408783}, "Confidence": 98.1492919921875}], "Parents": [{"Name": "Accessories"}, {"Name": "Gemstone"}, {"Name": "Jewelry"}], "Aliases": [], "Categories": [{"Name": "Apparel and Accessories"}]}, {"Name": "Gemstone", "Confidence": 100.0, "Instances": [], "Parents": [{"Name": "Accessories"}, {"Name": "Jewelry"}], "Aliases": [], "Categories": [{"Name": "Apparel and Accessories"}]}, {"Name": "Jewelry", "Confidence": 100.0, "Instances": [], "Parents": [{"Name": "Accessories"}], "Aliases": [], "Categories": [{"Name": "Apparel and Accessories"}]}], "experiments/valence/pleasant-1/flower1_google.jpeg": [{"Name": "Flower", "Confidence": 100.0, "Instances": [], "Parents": [{"Name": "Plant"}], "Aliases": [{"Name": "Blossom"}], "Categories": [{"Name": "Plants and Flowers"}]}, {"Name": "Plant", "Confidence": 100.0, "Instances": [], "Parents": [], "Aliases": [], "Categories": [{"Name": "Plants and Flowers"}]}, {"Name": "Rose", "Confidence": 100.0, "Instances": [{"BoundingBox": {"Width": 0.5703627467155457, "Height": 0.5831040740013123, "Left": 0.1313636749982834, "Top": 0.08569333702325821}, "Confidence": 99.61418151855469}], "Parents": [{"Name": "Flower"}, {"Name": "Plant"}], "Aliases": [], "Categories": [{"Name": "Plants and Flowers"}]}, {"Name": "Petal", "Confidence": 55.23131561279297, "Instances": [], "Parents": [{"Name": "Flower"}, {"Name": "Plant"}], "Aliases": [], "Categories": [{"Name": "Plants and Flowers"}]}], "experiments/valence/pleasant-1/gold1_google.jpeg": [{"Name": "Gold", "Confidence": 99.99998474121094, "Instances": [], "Parents": [], "Aliases": [], "Categories": [{"Name": "Materials"}]}, {"Name": "Treasure", "Confidence": 99.88420867919922, "Instances": [], "Parents": [], "Aliases": [], "Categories": [{"Name": "Buildings and Architecture"}]}, {"Name": "Box", "Confidence": 95.80894470214844, "Instances": [{"BoundingBox": {"Width": 0.474822461605072, "Height": 0.5216950178146362, "Left": 0.25612205266952515, "Top": 0.04512372985482216}, "Confidence": 95.80894470214844}, {"BoundingBox": {"Width": 0.2218388319015503, "Height": 0.21735315024852753, "Left": 0.5094980001449585, "Top": 0.6254633069038391}, "Confidence": 94.112548828125}, {"BoundingBox": {"Width": 0.47400954365730286, "Height": 0.5164874792098999, "Left": 0.15299005806446075, "Top": 0.2406775951385498}, "Confidence": 93.7496566772461}], "Parents": [], "Aliases": [], "Categories": [{"Name": "Apparel and Accessories"}]}], "experiments/valence/pleasant-1/money1_google.jpg": [{"Name": "Money", "Confidence": 99.4030532836914, "Instances": [], "Parents": [], "Aliases": [], "Categories": [{"Name": "Everyday Objects"}]}, {"Name": "Dollar", "Confidence": 98.77788543701172, "Instances": [], "Parents": [{"Name": "Money"}], "Aliases": [], "Categories": [{"Name": "Everyday Objects"}]}, {"Name": "Adult", "Confidence": 91.47187805175781, "Instances": [{"BoundingBox": {"Width": 0.24969542026519775, "Height": 0.32927319407463074, "Left": 0.321656197309494, "Top": 0.299678772687912}, "Confidence": 91.47187805175781}], "Parents": [{"Name": "Person"}], "Aliases": [], "Categories": [{"Name": "Person Description"}]}, {"Name": "Male", "Confidence": 91.47187805175781, "Instances": [{"BoundingBox": {"Width": 0.24969542026519775, "Height": 0.32927319407463074, "Left": 0.321656197309494, "Top": 0.299678772687912}, "Confidence": 91.47187805175781}], "Parents": [{"Name": "Person"}], "Aliases": [], "Categories": [{"Name": "Person Description"}]}, {"Name": "Man", "Confidence": 91.47187805175781, "Instances": [{"BoundingBox": {"Width": 0.24969542026519775, "Height": 0.32927319407463074, "Left": 0.321656197309494, "Top": 0.299678772687912}, "Confidence": 91.47187805175781}], "Parents": [{"Name": "Adult"}, {"Name": "Male"}, {"Name": "Person"}], "Aliases": [], "Categories": [{"Name": "Person Description"}]}, {"Name": "Person", "Confidence": 91.47187805175781, "Instances": [{"BoundingBox": {"Width": 0.24969542026519775, "Height": 0.32927319407463074, "Left": 0.321656197309494, "Top": 0.299678772687912}, "Confidence": 91.47187805175781}], "Parents": [], "Aliases": [{"Name": "Human"}], "Categories": [{"Name": "Person Description"}]}, {"Name": "Smoke Pipe", "Confidence": 64.25067901611328, "Instances": [{"BoundingBox": {"Width": 0.9172218441963196, "Height": 0.5319785475730896, "Left": 0.03208233043551445, "Top": 0.23832954466342926}, "Confidence": 64.25067901611328}], "Parents": [], "Aliases": [], "Categories": [{"Name": "Hobbies and Interests"}]}], "experiments/valence/pleasant-1/ocean1_cifar.png": [{"Name": "Animal", "Confidence": 99.99922180175781, "Instances": [], "Parents": [], "Aliases": [], "Categories": [{"Name": "Animals and Pets"}]}, {"Name": "Beak", "Confidence": 99.99922180175781, "Instances": [], "Parents": [{"Name": "Animal"}, {"Name": "Bird"}], "Aliases": [], "Categories": [{"Name": "Animals and Pets"}]}, {"Name": "Rock", "Confidence": 99.9635009765625, "Instances": [], "Parents": [], "Aliases": [], "Categories": [{"Name": "Nature and Outdoors"}]}, {"Name": "Nature", "Confidence": 99.72801208496094, "Instances": [], "Parents": [{"Name": "Outdoors"}], "Aliases": [], "Categories": [{"Name": "Nature and Outdoors"}]}, {"Name": "Outdoors", "Confidence": 99.72801208496094, "Instances": [], "Parents": [], "Aliases": [], "Categories": [{"Name": "Nature and Outdoors"}]}, {"Name": "Sky", "Confidence": 99.72801208496094, "Instances": [], "Parents": [{"Name": "Nature"}, {"Name": "Outdoors"}], "Aliases": [], "Categories": [{"Name": "Nature and Outdoors"}]}, {"Name": "Beach", "Confidence": 96.88429260253906, "Instances": [], "Parents": [{"Name": "Coast"}, {"Name": "Nature"}, {"Name": "Outdoors"}, {"Name": "Sea"}, {"Name": "Shoreline"}, {"Name": "Water"}], "Aliases": [], "Categories": [{"Name": "Nature and Outdoors"}]}, {"Name": "Coast", "Confidence": 96.88429260253906, "Instances": [], "Parents": [{"Name": "Nature"}, {"Name": "Outdoors"}, {"Name": "Sea"}, {"Name": "Shoreline"}, {"Name": "Water"}], "Aliases": [], "Categories": [{"Name": "Nature and Outdoors"}]}, {"Name": "Sea", "Confidence": 96.88429260253906, "Instances": [], "Parents": [{"Name": "Nature"}, {"Name": "Outdoors"}, {"Name": "Water"}], "Aliases": [{"Name": "Ocean"}], "Categories": [{"Name": "Nature and Outdoors"}]}, {"Name": "Shoreline", "Confidence": 96.88429260253906, "Instances": [], "Parents": [{"Name": "Water"}], "Aliases": [], "Categories": [{"Name": "Nature and Outdoors"}]}, {"Name": "Water", "Confidence": 96.88429260253906, "Instances": [], "Parents": [], "Aliases": [], "Categories": [{"Name": "Nature and Outdoors"}]}, {"Name": "Flower", "Confidence": 64.2654037475586, "Instances": [], "Parents": [{"Name": "Plant"}], "Aliases": [{"Name": "Blossom"}], "Categories": [{"Name": "Plants and Flowers"}]}, {"Name": "Fruit", "Confidence": 63.62268829345703, "Instances": [], "Parents": [{"Name": "Food"}, {"Name": "Plant"}, {"Name": "Produce"}], "Aliases": [], "Categories": [{"Name": "Food and Beverage"}]}, {"Name": "Sailboat", "Confidence": 57.52640914916992, "Instances": [], "Parents": [{"Name": "Boat"}, {"Name": "Transportation"}, {"Name": "Vehicle"}], "Aliases": [], "Categories": [{"Name": "Vehicles and Automotive"}]}, {"Name": "Horizon", "Confidence": 57.156978607177734, "Instances": [], "Parents": [{"Name": "Nature"}, {"Name": "Outdoors"}, {"Name": "Sky"}], "Aliases": [], "Categories": [{"Name": "Nature and Outdoors"}]}, {"Name": "Barefoot", "Confidence": 56.691444396972656, "Instances": [], "Parents": [{"Name": "Person"}], "Aliases": [], "Categories": [{"Name": "Person Description"}]}, {"Name": "Tennis Ball", "Confidence": 56.65717697143555, "Instances": [], "Parents": [{"Name": "Ball"}, {"Name": "Sport"}, {"Name": "Tennis"}], "Aliases": [], "Categories": [{"Name": "Sports"}]}, {"Name": "Pebble", "Confidence": 55.55205535888672, "Instances": [], "Parents": [], "Aliases": [], "Categories": [{"Name": "Nature and Outdoors"}]}, {"Name": "Sea Life", "Confidence": 55.43281936645508, "Instances": [], "Parents": [{"Name": "Animal"}], "Aliases": [], "Categories": [{"Name": "Animals and Pets"}]}, {"Name": "Mammal", "Confidence": 55.424644470214844, "Instances": [], "Parents": [{"Name": "Animal"}], "Aliases": [], "Categories": [{"Name": "Animals and Pets"}]}], "experiments/valence/pleasant-1/rainbow1_google.jpg": [{"Name": "Nature", "Confidence": 100.0, "Instances": [], "Parents": [{"Name": "Outdoors"}], "Aliases": [], "Categories": [{"Name": "Nature and Outdoors"}]}, {"Name": "Outdoors", "Confidence": 100.0, "Instances": [], "Parents": [], "Aliases": [], "Categories": [{"Name": "Nature and Outdoors"}]}, {"Name": "Sky", "Confidence": 100.0, "Instances": [], "Parents": [{"Name": "Nature"}, {"Name": "Outdoors"}], "Aliases": [], "Categories": [{"Name": "Nature and Outdoors"}]}, {"Name": "Rainbow", "Confidence": 99.98987579345703, "Instances": [], "Parents": [{"Name": "Nature"}, {"Name": "Outdoors"}, {"Name": "Sky"}], "Aliases": [], "Categories": [{"Name": "Nature and Outdoors"}]}, {"Name": "Azure Sky", "Confidence": 97.80460357666016, "Instances": [], "Parents": [{"Name": "Nature"}, {"Name": "Outdoors"}, {"Name": "Sky"}], "Aliases": [], "Categories": [{"Name": "Nature and Outdoors"}]}, {"Name": "Disk", "Confidence": 64.37147521972656, "Instances": [{"BoundingBox": {"Width": 0.9302104711532593, "Height": 0.9397539496421814, "Left": 0.0670194923877716, "Top": 0.04810871556401253}, "Confidence": 64.37147521972656}], "Parents": [], "Aliases": [], "Categories": [{"Name": "Technology and Computing"}]}, {"Name": "Cloud", "Confidence": 57.41730499267578, "Instances": [], "Parents": [{"Name": "Nature"}, {"Name": "Outdoors"}, {"Name": "Sky"}], "Aliases": [], "Categories": [{"Name": "Nature and Outdoors"}]}, {"Name": "Scenery", "Confidence": 55.3726806640625, "Instances": [], "Parents": [{"Name": "Nature"}, {"Name": "Outdoors"}], "Aliases": [], "Categories": [{"Name": "Nature and Outdoors"}]}], "experiments/valence/pleasant-1/sunrise1_google.jpeg": [{"Name": "Nature", "Confidence": 100.0, "Instances": [], "Parents": [{"Name": "Outdoors"}], "Aliases": [], "Categories": [{"Name": "Nature and Outdoors"}]}, {"Name": "Outdoors", "Confidence": 100.0, "Instances": [], "Parents": [], "Aliases": [], "Categories": [{"Name": "Nature and Outdoors"}]}, {"Name": "Sky", "Confidence": 100.0, "Instances": [], "Parents": [{"Name": "Nature"}, {"Name": "Outdoors"}], "Aliases": [], "Categories": [{"Name": "Nature and Outdoors"}]}, {"Name": "Sun", "Confidence": 99.99938201904297, "Instances": [], "Parents": [{"Name": "Nature"}, {"Name": "Outdoors"}, {"Name": "Sky"}], "Aliases": [], "Categories": [{"Name": "Nature and Outdoors"}]}, {"Name": "Sunrise", "Confidence": 99.97415161132812, "Instances": [], "Parents": [{"Name": "Nature"}, {"Name": "Outdoors"}, {"Name": "Sky"}], "Aliases": [], "Categories": [{"Name": "Nature and Outdoors"}]}, {"Name": "Sunlight", "Confidence": 99.88764953613281, "Instances": [], "Parents": [], "Aliases": [], "Categories": [{"Name": "Nature and Outdoors"}]}, {"Name": "Scenery", "Confidence": 99.11682891845703, "Instances": [], "Parents": [{"Name": "Nature"}, {"Name": "Outdoors"}], "Aliases": [], "Categories": [{"Name": "Nature and Outdoors"}]}, {"Name": "Flare", "Confidence": 98.7145767211914, "Instances": [], "Parents": [{"Name": "Light"}], "Aliases": [], "Categories": [{"Name": "Colors and Visual Composition"}]}, {"Name": "Light", "Confidence": 98.7145767211914, "Instances": [], "Parents": [], "Aliases": [], "Categories": [{"Name": "Colors and Visual Composition"}]}, {"Name": "Horizon", "Confidence": 88.18170166015625, "Instances": [], "Parents": [{"Name": "Nature"}, {"Name": "Outdoors"}, {"Name": "Sky"}], "Aliases": [], "Categories": [{"Name": "Nature and Outdoors"}]}, {"Name": "Sunset", "Confidence": 76.52806091308594, "Instances": [], "Parents": [{"Name": "Nature"}, {"Name": "Outdoors"}, {"Name": "Sky"}], "Aliases": [{"Name": "Dusk"}, {"Name": "Dawn"}, {"Name": "Red Sky"}], "Categories": [{"Name": "Nature and Outdoors"}]}, {"Name": "Landscape", "Confidence": 76.49129486083984, "Instances": [], "Parents": [{"Name": "Nature"}, {"Name": "Outdoors"}], "Aliases": [], "Categories": [{"Name": "Nature and Outdoors"}]}, {"Name": "Cloud", "Confidence": 56.6907958984375, "Instances": [], "Parents": [{"Name": "Nature"}, {"Name": "Outdoors"}, {"Name": "Sky"}], "Aliases": [], "Categories": [{"Name": "Nature and Outdoors"}]}, {"Name": "Person", "Confidence": 56.49455261230469, "Instances": [{"BoundingBox": {"Width": 0.030122680589556694, "Height": 0.02869097888469696, "Left": 0.9087243676185608, "Top": 0.971267819404602}, "Confidence": 56.49455261230469}], "Parents": [], "Aliases": [{"Name": "Human"}], "Categories": [{"Name": "Person Description"}]}], "experiments/valence/pleasant-1/sunset1_google.jpeg": [{"Name": "Nature", "Confidence": 99.99998474121094, "Instances": [], "Parents": [{"Name": "Outdoors"}], "Aliases": [], "Categories": [{"Name": "Nature and Outdoors"}]}, {"Name": "Outdoors", "Confidence": 99.99998474121094, "Instances": [], "Parents": [], "Aliases": [], "Categories": [{"Name": "Nature and Outdoors"}]}, {"Name": "Sky", "Confidence": 99.99998474121094, "Instances": [], "Parents": [{"Name": "Nature"}, {"Name": "Outdoors"}], "Aliases": [], "Categories": [{"Name": "Nature and Outdoors"}]}, {"Name": "Horizon", "Confidence": 99.99667358398438, "Instances": [], "Parents": [{"Name": "Nature"}, {"Name": "Outdoors"}, {"Name": "Sky"}], "Aliases": [], "Categories": [{"Name": "Nature and Outdoors"}]}, {"Name": "Scenery", "Confidence": 99.90235900878906, "Instances": [], "Parents": [{"Name": "Nature"}, {"Name": "Outdoors"}], "Aliases": [], "Categories": [{"Name": "Nature and Outdoors"}]}, {"Name": "Sea", "Confidence": 98.6872329711914, "Instances": [], "Parents": [{"Name": "Nature"}, {"Name": "Outdoors"}, {"Name": "Water"}], "Aliases": [{"Name": "Ocean"}], "Categories": [{"Name": "Nature and Outdoors"}]}, {"Name": "Water", "Confidence": 98.6872329711914, "Instances": [], "Parents": [], "Aliases": [], "Categories": [{"Name": "Nature and Outdoors"}]}, {"Name": "Sunrise", "Confidence": 96.40483856201172, "Instances": [], "Parents": [{"Name": "Nature"}, {"Name": "Outdoors"}, {"Name": "Sky"}], "Aliases": [], "Categories": [{"Name": "Nature and Outdoors"}]}, {"Name": "Beach", "Confidence": 95.25399780273438, "Instances": [], "Parents": [{"Name": "Coast"}, {"Name": "Nature"}, {"Name": "Outdoors"}, {"Name": "Sea"}, {"Name": "Shoreline"}, {"Name": "Water"}], "Aliases": [], "Categories": [{"Name": "Nature and Outdoors"}]}, {"Name": "Coast", "Confidence": 95.25399780273438, "Instances": [], "Parents": [{"Name": "Nature"}, {"Name": "Outdoors"}, {"Name": "Sea"}, {"Name": "Shoreline"}, {"Name": "Water"}], "Aliases": [], "Categories": [{"Name": "Nature and Outdoors"}]}, {"Name": "Shoreline", "Confidence": 95.25399780273438, "Instances": [], "Parents": [{"Name": "Water"}], "Aliases": [], "Categories": [{"Name": "Nature and Outdoors"}]}, {"Name": "Landscape", "Confidence": 89.26118469238281, "Instances": [], "Parents": [{"Name": "Nature"}, {"Name": "Outdoors"}], "Aliases": [], "Categories": [{"Name": "Nature and Outdoors"}]}, {"Name": "Panoramic", "Confidence": 60.87553024291992, "Instances": [], "Parents": [{"Name": "Landscape"}, {"Name": "Nature"}, {"Name": "Outdoors"}, {"Name": "Scenery"}], "Aliases": [], "Categories": [{"Name": "Nature and Outdoors"}]}, {"Name": "Sunset", "Confidence": 57.37679672241211, "Instances": [], "Parents": [{"Name": "Nature"}, {"Name": "Outdoors"}, {"Name": "Sky"}], "Aliases": [{"Name": "Dusk"}, {"Name": "Dawn"}, {"Name": "Red Sky"}], "Categories": [{"Name": "Nature and Outdoors"}]}, {"Name": "Sunlight", "Confidence": 55.59850311279297, "Instances": [], "Parents": [], "Aliases": [], "Categories": [{"Name": "Nature and Outdoors"}]}, {"Name": "Sun", "Confidence": 55.306880950927734, "Instances": [], "Parents": [{"Name": "Nature"}, {"Name": "Outdoors"}, {"Name": "Sky"}], "Aliases": [], "Categories": [{"Name": "Nature and Outdoors"}]}]}